jobv1/__init__.py
jobv1/client/__init__.py
jobv1/client/job_api_base.py
jobv1/client/job_api_event.py
jobv1/client/job_api_job.py
jobv1/client/job_api_metric.py
jobv1/client/job_api_task.py
jobv1/client/job_client.py
jobv1/tracker/__init__.py
jobv1/tracker/tracker.py
jobv1-0.0.3.dist-info/METADATA
jobv1-0.0.3.dist-info/WHEEL
jobv1-0.0.3.dist-info/top_level.txt
jobv1-0.0.3.dist-info/RECORD
